grvtree/__init__.py
grvtree-0.3.0.dist-info/METADATA
grvtree-0.3.0.dist-info/WHEEL
grvtree-0.3.0.dist-info/RECORD
