Metadata-Version: 2.1
Name: grvtree
Version: 0.3.0
Summary: An implementation of Gómez-Rodríguez and Vilares' tree linearization
Home-page: https://pypi.org/project/grvtree/
License: Apache-2.0
Author: Nori Hayashi
Author-email: net@hayashi-lin.net
Requires-Python: >=3.11,<4.0
Classifier: License :: OSI Approved :: Apache Software License
Classifier: Programming Language :: Python :: 3
Classifier: Programming Language :: Python :: 3.11
Classifier: Programming Language :: Python :: 3.12
Requires-Dist: more-itertools (>=10.2.0,<11.0.0)
Requires-Dist: nltk (>=3.8.1,<4.0.0)
Requires-Dist: nltk-tree-extensions (>=3.7.0.2.0,<4.0.0.0.0)
Project-URL: Repository, https://github.com/aslemen/GRV-tree
